<?xml version="1.0" encoding="utf-8"?><ArrayOfOrderItem xmlns:xsi="http://www.w3.org/2001/XMLSchema-instance" xmlns:xsd="http://www.w3.org/2001/XMLSchema"><OrderItem><ID>0</ID><ProductId>100000</ProductId><OrderId>0</OrderId><Price>140000</Price><Amount>1</Amount></OrderItem><OrderItem><ID>1</ID><ProductId>100001</ProductId><OrderId>0</OrderId><Price>70000</Price><Amount>2</Amount></OrderItem><OrderItem><ID>2</ID><ProductId>100000</ProductId><OrderId>1</OrderId><Price>140000</Price><Amount>1</Amount></OrderItem><OrderItem><ID>3</ID><ProductId>100001</ProductId><OrderId>1</OrderId><Price>70000</Price><Amount>2</Amount></OrderItem><OrderItem><ID>4</ID><ProductId>100000</ProductId><OrderId>2</OrderId><Price>140000</Price><Amount>1</Amount></OrderItem><OrderItem><ID>5</ID><ProductId>100001</ProductId><OrderId>2</OrderId><Price>70000</Price><Amount>2</Amount></OrderItem><OrderItem><ID>6</ID><ProductId>100000</ProductId><OrderId>3</OrderId><Price>140000</Price><Amount>1</Amount></OrderItem><OrderItem><ID>7</ID><ProductId>100001</ProductId><OrderId>3</OrderId><Price>70000</Price><Amount>2</Amount></OrderItem><OrderItem><ID>8</ID><ProductId>100000</ProductId><OrderId>4</OrderId><Price>140000</Price><Amount>1</Amount></OrderItem><OrderItem><ID>9</ID><ProductId>100001</ProductId><OrderId>4</OrderId><Price>70000</Price><Amount>2</Amount></OrderItem><OrderItem><ID>10</ID><ProductId>100000</ProductId><OrderId>5</OrderId><Price>140000</Price><Amount>1</Amount></OrderItem><OrderItem><ID>11</ID><ProductId>100001</ProductId><OrderId>5</OrderId><Price>70000</Price><Amount>2</Amount></OrderItem><OrderItem><ID>12</ID><ProductId>100000</ProductId><OrderId>6</OrderId><Price>140000</Price><Amount>1</Amount></OrderItem><OrderItem><ID>13</ID><ProductId>100001</ProductId><OrderId>6</OrderId><Price>70000</Price><Amount>2</Amount></OrderItem><OrderItem><ID>14</ID><ProductId>100000</ProductId><OrderId>7</OrderId><Price>140000</Price><Amount>1</Amount></OrderItem><OrderItem><ID>15</ID><ProductId>100001</ProductId><OrderId>7</OrderId><Price>70000</Price><Amount>2</Amount></OrderItem><OrderItem><ID>16</ID><ProductId>100000</ProductId><OrderId>8</OrderId><Price>140000</Price><Amount>1</Amount></OrderItem><OrderItem><ID>17</ID><ProductId>100001</ProductId><OrderId>8</OrderId><Price>70000</Price><Amount>2</Amount></OrderItem><OrderItem><ID>18</ID><ProductId>100000</ProductId><OrderId>9</OrderId><Price>140000</Price><Amount>1</Amount></OrderItem><OrderItem><ID>19</ID><ProductId>100001</ProductId><OrderId>9</OrderId><Price>70000</Price><Amount>2</Amount></OrderItem><OrderItem><ID>20</ID><ProductId>100000</ProductId><OrderId>10</OrderId><Price>140000</Price><Amount>1</Amount></OrderItem><OrderItem><ID>21</ID><ProductId>100001</ProductId><OrderId>10</OrderId><Price>70000</Price><Amount>2</Amount></OrderItem><OrderItem><ID>22</ID><ProductId>100000</ProductId><OrderId>11</OrderId><Price>140000</Price><Amount>1</Amount></OrderItem><OrderItem><ID>23</ID><ProductId>100001</ProductId><OrderId>11</OrderId><Price>70000</Price><Amount>2</Amount></OrderItem><OrderItem><ID>24</ID><ProductId>100000</ProductId><OrderId>12</OrderId><Price>140000</Price><Amount>1</Amount></OrderItem><OrderItem><ID>25</ID><ProductId>100001</ProductId><OrderId>12</OrderId><Price>70000</Price><Amount>2</Amount></OrderItem><OrderItem><ID>26</ID><ProductId>100000</ProductId><OrderId>13</OrderId><Price>140000</Price><Amount>1</Amount></OrderItem><OrderItem><ID>27</ID><ProductId>100001</ProductId><OrderId>13</OrderId><Price>70000</Price><Amount>2</Amount></OrderItem><OrderItem><ID>28</ID><ProductId>100000</ProductId><OrderId>14</OrderId><Price>140000</Price><Amount>1</Amount></OrderItem><OrderItem><ID>29</ID><ProductId>100001</ProductId><OrderId>14</OrderId><Price>70000</Price><Amount>2</Amount></OrderItem><OrderItem><ID>30</ID><ProductId>100000</ProductId><OrderId>15</OrderId><Price>140000</Price><Amount>1</Amount></OrderItem><OrderItem><ID>31</ID><ProductId>100001</ProductId><OrderId>15</OrderId><Price>70000</Price><Amount>2</Amount></OrderItem><OrderItem><ID>32</ID><ProductId>100000</ProductId><OrderId>16</OrderId><Price>140000</Price><Amount>1</Amount></OrderItem><OrderItem><ID>33</ID><ProductId>100001</ProductId><OrderId>16</OrderId><Price>70000</Price><Amount>2</Amount></OrderItem><OrderItem><ID>34</ID><ProductId>100000</ProductId><OrderId>17</OrderId><Price>140000</Price><Amount>1</Amount></OrderItem><OrderItem><ID>35</ID><ProductId>100001</ProductId><OrderId>17</OrderId><Price>70000</Price><Amount>2</Amount></OrderItem><OrderItem><ID>36</ID><ProductId>100000</ProductId><OrderId>18</OrderId><Price>140000</Price><Amount>1</Amount></OrderItem><OrderItem><ID>37</ID><ProductId>100001</ProductId><OrderId>18</OrderId><Price>70000</Price><Amount>2</Amount></OrderItem><OrderItem><ID>38</ID><ProductId>100000</ProductId><OrderId>19</OrderId><Price>140000</Price><Amount>1</Amount></OrderItem><OrderItem><ID>39</ID><ProductId>100001</ProductId><OrderId>19</OrderId><Price>70000</Price><Amount>2</Amount></OrderItem></ArrayOfOrderItem>